stashhouse_tftp/__init__.py
stashhouse_tftp/file_io.py
stashhouse_tftp/protocols.py
stashhouse_tftp-0.0.2.dist-info/METADATA
stashhouse_tftp-0.0.2.dist-info/WHEEL
stashhouse_tftp-0.0.2.dist-info/entry_points.txt
stashhouse_tftp-0.0.2.dist-info/licenses/LICENSE
stashhouse_tftp-0.0.2.dist-info/RECORD
