Metadata-Version: 2.4
Name: stashhouse-tftp
Version: 0.0.2
Summary: StashHouse plugin for Trivial File Transfer Protocol (TFTP)
Project-URL: Homepage, https://github.com/Jayson-Fong/stashhouse-tftp
Project-URL: Issues, https://github.com/Jayson-Fong/stashhouse-tftp/issues
Author-email: Jayson Fong <jayson.fong@gatech.edu>
License: MIT
License-File: LICENSE
Classifier: Development Status :: 1 - Planning
Classifier: Framework :: AsyncIO
Classifier: License :: OSI Approved :: MIT License
Classifier: Operating System :: OS Independent
Classifier: Programming Language :: Python
Classifier: Programming Language :: Python :: 3.11
Classifier: Programming Language :: Python :: 3.12
Classifier: Programming Language :: Python :: 3.13
Classifier: Topic :: Communications :: File Sharing
Classifier: Typing :: Typed
Requires-Python: >=3.11
Requires-Dist: py3tftp==1.3.0
Requires-Dist: stashhouse==0.0.4
